main.py
mcp_server.py
osc_daemon.py
iflow_mcp_nikmaniatis_pd_mcp_server-0.1.2.dist-info/METADATA
iflow_mcp_nikmaniatis_pd_mcp_server-0.1.2.dist-info/WHEEL
iflow_mcp_nikmaniatis_pd_mcp_server-0.1.2.dist-info/entry_points.txt
iflow_mcp_nikmaniatis_pd_mcp_server-0.1.2.dist-info/top_level.txt
iflow_mcp_nikmaniatis_pd_mcp_server-0.1.2.dist-info/RECORD
