Metadata-Version: 2.4
Name: iflow-mcp_nikmaniatis_pd-mcp-server
Version: 0.1.2
Summary: A Model Context Protocol (MCP) server for Pure Data, an open-source visual programming language and patchable environment for real-time computer music.
Author: nikmaniatis
Requires-Python: >=3.11
Requires-Dist: argparse>=1.4.0
Requires-Dist: asyncio>=3.4.3
Requires-Dist: jsonschema>=4.23.0
Requires-Dist: mcp[cli]>=1.4.1
Requires-Dist: python-osc>=1.9.3
Dynamic: author
Dynamic: requires-python
